sfn_blueprint/__init__.py
sfn_blueprint/agents/__init__.py
sfn_blueprint/agents/base_agent.py
sfn_blueprint/agents/code_executor.py
sfn_blueprint/agents/code_generator.py
sfn_blueprint/agents/data_analyzer.py
sfn_blueprint/agents/suggestions_generator.py
sfn_blueprint/agents/validate_and_retry_agent.py
sfn_blueprint/config/__init__.py
sfn_blueprint/config/config_manager.py
sfn_blueprint/config/model_config.py
sfn_blueprint/config/prompts_config.json
sfn_blueprint/core/engine.py
sfn_blueprint/graph/chat_graph.py
sfn_blueprint/graph/reflection_graph.py
sfn_blueprint/prompts/prompt_template.py
sfn_blueprint/prompts/reflection_prompt.py
sfn_blueprint/schema/schema.py
sfn_blueprint/tasks/__init__.py
sfn_blueprint/tasks/task.py
sfn_blueprint/tools/tool.py
sfn_blueprint/utils/__init__.py
sfn_blueprint/utils/context_helper.py
sfn_blueprint/utils/context_manager.py
sfn_blueprint/utils/context_utils.py
sfn_blueprint/utils/cost_callback.py
sfn_blueprint/utils/custom_exceptions.py
sfn_blueprint/utils/data_loader.py
sfn_blueprint/utils/data_post_processor.py
sfn_blueprint/utils/langgraph_logging.py
sfn_blueprint/utils/llm_config_stub.py
sfn_blueprint/utils/llm_response_formatter.py
sfn_blueprint/utils/logging.py
sfn_blueprint/utils/prompt_manager.py
sfn_blueprint/utils/session_manager.py
sfn_blueprint/utils/sql_auto_corrector.py
sfn_blueprint/utils/workflow_storage.py
sfn_blueprint/utils/llm_handler/__init__.py
sfn_blueprint/utils/llm_handler/llm_clients.py
sfn_blueprint/utils/llm_handler/llm_langchain_client.py
sfn_blueprint/views/__init__.py
sfn_blueprint/views/base_view.py
sfn_blueprint/views/streamlit_view.py
sfn_blueprint-0.7.4.dist-info/METADATA
sfn_blueprint-0.7.4.dist-info/WHEEL
sfn_blueprint-0.7.4.dist-info/top_level.txt
sfn_blueprint-0.7.4.dist-info/RECORD
