Metadata-Version: 2.4
Name: sfn_blueprint
Version: 0.7.4
Summary: sfn-blueprint is a modular framework that enables rapid building of AI Agents, offering both flexibility and ease of customization.
Author-email: Rajesh Darak <rajesh@stepfuction.ai>
License-Expression: MIT
Project-URL: Homepage, https://github.com/iamrajeshdaraksfn/sfn_blueprint
Project-URL: Repository, https://github.com/iamrajeshdaraksfn/sfn_blueprint
Classifier: Programming Language :: Python :: 3
Classifier: Programming Language :: Python :: 3.10
Classifier: Programming Language :: Python :: 3.11
Classifier: Programming Language :: Python :: 3.12
Classifier: Programming Language :: Python :: 3.13
Classifier: Operating System :: OS Independent
Requires-Python: <3.13,>=3.10
Requires-Dist: sfn-llm-client==0.3.4
Requires-Dist: openai>=1.99.9
Requires-Dist: python-dotenv>=1.0.0
Requires-Dist: textblob>=0.18.0
Requires-Dist: scikit-learn>=1.5.2
Requires-Dist: nltk>=3.9.1
Requires-Dist: spacy>=3.8.2
Requires-Dist: pyyaml>=6.0
Requires-Dist: pytest>=8.3.4
Requires-Dist: cloudpickle
Requires-Dist: dask[dataframe]>=2024.8.0
Requires-Dist: dask[delayed]>=2024.8.0
Requires-Dist: openpyxl>=3.1.5
Requires-Dist: snowflake-connector-python>=3.17.0
Requires-Dist: snowflake-ml-python>=1.9.0
Requires-Dist: snowflake-snowpark-python>=1.26.0
Requires-Dist: langgraph>=0.6.3
Requires-Dist: mlflow-tracing>=3.3.2
Requires-Dist: sfn-db-query-builder>=2.0
Requires-Dist: langchain-classic==1.0.1
